micro_manager/__init__.py
micro_manager/__main__.py
micro_manager/config.py
micro_manager/domain_decomposition.py
micro_manager/interpolation.py
micro_manager/micro_manager.py
micro_manager/micro_manager_base.py
micro_manager/micro_simulation.py
micro_manager/adaptivity/__init__.py
micro_manager/adaptivity/adaptivity.py
micro_manager/adaptivity/global_adaptivity.py
micro_manager/adaptivity/local_adaptivity.py
micro_manager/snapshot/__init__.py
micro_manager/snapshot/dataset.py
micro_manager/snapshot/snapshot.py
micro_manager/tools/__init__.py
micro_manager/tools/logging_wrapper.py
micro_manager_precice-0.7.0.dist-info/licenses/LICENSE
micro_manager_precice-0.7.0.dist-info/METADATA
micro_manager_precice-0.7.0.dist-info/WHEEL
micro_manager_precice-0.7.0.dist-info/entry_points.txt
micro_manager_precice-0.7.0.dist-info/top_level.txt
micro_manager_precice-0.7.0.dist-info/RECORD
