Metadata-Version: 2.4
Name: micro-manager-precice
Version: 0.7.0
Summary: A tool which facilitates two-scale macro-micro coupled simulations using preCICE.
Author-email: The preCICE Developers <info@precice.org>
Maintainer-email: Ishaan Desai <ishaan.desai@ipvs.uni-stuttgart.de>
License: GPLv3
Project-URL: Homepage, https://precice.org
Project-URL: Documentation, https://precice.org/tooling-micro-manager-overview.html
Project-URL: Repository, https://github.com/precice/micro-manager
Project-URL: Bug Tracker, https://github.com/precice/micro-manager/issues
Keywords: preCICE,multiscale,coupling
Classifier: Development Status :: 4 - Beta
Classifier: License :: OSI Approved :: GNU General Public License v3 (GPLv3)
Classifier: Programming Language :: Python :: 3 :: Only
Classifier: Programming Language :: Python :: 3.8
Classifier: Topic :: Scientific/Engineering
Requires-Python: >=3.8
License-File: LICENSE
Requires-Dist: pyprecice>=3.2
Requires-Dist: numpy
Requires-Dist: mpi4py
Requires-Dist: psutil
Provides-Extra: snapshot
Requires-Dist: h5py; extra == "snapshot"
Provides-Extra: sklearn
Requires-Dist: scikit-learn; extra == "sklearn"
Dynamic: license-file
